[
 {
  "title": "スジさんの読書時間",
  "summary": "公園で本を読み、忘れそうになったスジさんの話"
 },
 {
  "title": "初めてのケーキ",
  "summary": "ミナさんが初めてケーキ作りに挑戦する話"
 },
 {
  "title": "ハナの特別な石",
  "summary": "ハナが散歩中に見つけた、小さな石の物語。"
 },
 {
  "title": "ソラさんの美味しい夕食",
  "summary": "ソラさんが夕食の料理を作り、楽しむ話。"
 },
 {
  "title": "新しい庭を見つけて",
  "summary": "ジミンさんが散歩中に美しい秘密の庭を発見する話。"
 },
 {
  "title": "小さな植物の喜び",
  "summary": "一人の女性が、小さな植物を買って気分転換をする話。"
 },
 {
  "title": "ミンスの新しい趣味",
  "summary": "ミンスの新しい趣味についての短い話。"
 },
 {
  "title": "温かいカフェのひととき",
  "summary": "イェナがカフェで過ごす短いひとときの話"
 },
 {
  "title": "偶然出会った猫",
  "summary": "道で猫と出会った話"
 },
 {
  "title": "退勤後の温かい食事",
  "summary": "退勤後に市場で食材を買い、簡単な料理を作って食べる話。"
 },
 {
  "title": "小鳥のプレゼント",
  "summary": "道で迷った小鳥を助ける話。"
 },
 {
  "title": "古い郵便受け",
  "summary": "古い郵便受けに届いた、見知らぬ人からの小さな手紙の話。"
 }
]